setup.py
flask_paypal/__init__.py
flask_paypal/version.py
flask_paypal.egg-info/PKG-INFO
flask_paypal.egg-info/SOURCES.txt
flask_paypal.egg-info/dependency_links.txt
flask_paypal.egg-info/entry_points.txt
flask_paypal.egg-info/pbr.json
flask_paypal.egg-info/requires.txt
flask_paypal.egg-info/top_level.txt
tests/__init__.py
tests/base.py
tests/test_version.py