Metadata-Version: 1.1
Name: flask-paypal
Version: 0.1.0
Summary: Flask integration with PayPal, mainly focused on subscriptions.
Home-page: https://github.com/heynemann/flask-paypal
Author: Bernardo Heynemann
Author-email: heynemann@gmail.com
License: MIT
Keywords: paypal payment subscription flask jinja
Platform: UNKNOWN
Classifier: Development Status :: 4 - Beta
Classifier: Intended Audience :: Developers
Classifier: License :: OSI Approved :: MIT License
Classifier: Natural Language :: English
Classifier: Operating System :: Unix
Classifier: Programming Language :: Python :: 2.7
Classifier: Programming Language :: Python :: 3.4
Classifier: Programming Language :: Python :: Implementation :: PyPy
Classifier: Operating System :: OS Independent
